nqrduck_module/__init__.py
nqrduck_module/controller.py
nqrduck_module/model.py
nqrduck_module/module.py
nqrduck_module/view.py
nqrduck_module/widget.py
nqrduck_module/resources/module.ini
nqrduck_module/resources/module_widget.ui
nqrduck_module-0.0.2.dist-info/METADATA
nqrduck_module-0.0.2.dist-info/WHEEL
nqrduck_module-0.0.2.dist-info/entry_points.txt
nqrduck_module-0.0.2.dist-info/licenses/LICENSE
nqrduck_module-0.0.2.dist-info/RECORD
