Metadata-Version: 2.3
Name: nqrduck-module
Version: 0.0.2
Summary: A template for nqrduck modules. Also used for testing.
Project-URL: Homepage, https://nqrduck.cool
Project-URL: Bug Tracker, https://github.com/nqrduck/nqrduck-module/issues
Project-URL: Source Code, https://github.com/nqrduck/nqrduck-module
Author-email: jupfi <support@nqrduck.cool>
License: MIT License
License-File: LICENSE
Classifier: License :: OSI Approved :: MIT License
Classifier: Operating System :: OS Independent
Classifier: Programming Language :: Python :: 3
Requires-Python: >=3.8
Requires-Dist: matplotlib
Requires-Dist: nqrduck
Requires-Dist: pyqt6
